Metadata-Version: 1.0
Name: pykahoot
Version: 1.0.7
Summary: A working kahoot python API.
Home-page: UNKNOWN
Author: UNKNOWN
Author-email: UNKNOWN
License: UNKNOWN
Platform: UNKNOWN
